django_set_field/__init__.py
django_set_field/admin.py
django_set_field/debug.py
django_set_field/fields.py
django_set_field/forms.py
django_setfield-0.3.0.dist-info/LICENSE
django_setfield-0.3.0.dist-info/METADATA
django_setfield-0.3.0.dist-info/WHEEL
django_setfield-0.3.0.dist-info/RECORD
